qubelib/__init__.py
qubelib/main.py
qubelib-0.2.dist-info/METADATA
qubelib-0.2.dist-info/WHEEL
qubelib-0.2.dist-info/top_level.txt
qubelib-0.2.dist-info/RECORD
