Metadata-Version: 2.1
Name: qubelib
Version: 0.2
Summary: Qubelib for our new website, our github: https://github.com/RobloxFactoryRyaturmite/discordus/tree/main
Requires-Dist: pillow
